mc_git_test/__init__.py
mc_git_test/test.py
MobilityCapstone1-0.0.1.dist-info/METADATA
MobilityCapstone1-0.0.1.dist-info/WHEEL
MobilityCapstone1-0.0.1.dist-info/top_level.txt
MobilityCapstone1-0.0.1.dist-info/RECORD
